napari_piscis/__init__.py
napari_piscis/_version.py
napari_piscis/_widget.py
napari_piscis/napari.yaml
napari_piscis-0.1.22.dist-info/licenses/LICENSE
napari_piscis-0.1.22.dist-info/METADATA
napari_piscis-0.1.22.dist-info/WHEEL
napari_piscis-0.1.22.dist-info/entry_points.txt
napari_piscis-0.1.22.dist-info/top_level.txt
napari_piscis-0.1.22.dist-info/RECORD
