Metadata-Version: 2.4
Name: napari-piscis
Version: 0.1.22
Summary: Unofficial plugin for Piscis, a deep learning algorithm for spot detection.
Author-email: Michael Blodgett <michaelablodgett@gmail.com>
License: MIT License
Classifier: Development Status :: 2 - Pre-Alpha
Classifier: Framework :: napari
Classifier: Intended Audience :: Developers
Classifier: License :: OSI Approved :: MIT License
Classifier: Operating System :: OS Independent
Classifier: Programming Language :: Python
Classifier: Programming Language :: Python :: 3
Classifier: Programming Language :: Python :: 3 :: Only
Classifier: Programming Language :: Python :: 3.10
Classifier: Programming Language :: Python :: 3.11
Classifier: Programming Language :: Python :: 3.12
Classifier: Programming Language :: Python :: 3.13
Classifier: Topic :: Scientific/Engineering :: Image Processing
Requires-Python: <3.14,>=3.10
License-File: LICENSE
Requires-Dist: napari>=0.4.19
Requires-Dist: magicgui>=0.8
Requires-Dist: numpy
Requires-Dist: scikit-image
Requires-Dist: piscis>=0.2.7
Requires-Dist: jax<=0.4.30
Requires-Dist: loguru
Provides-Extra: all
Requires-Dist: napari[all]; extra == "all"
Dynamic: license-file
